[
  {
    "name": "Versammlung | Split 2 | Start in den neuen Split!",
    "description": "Treffen: 19:15 | Start: 19:30 - Pflicht für Teams.",
    "start": "2026-05-10T17:30:00+00:00",
    "location": "https://discord.gg/ultrainstinctcrew"
  },
  {
    "name": "UIC Prime vs Lunar Pugnacious Gaming",
    "description": "🏆 **Prime League Match**\n⚔️ **UIC Prime vs Lunar Pugnacious Gaming**\n\n*Die Roster sind noch nicht vollständig bestätigt. Das offizielle Scouting-Update folgt...*\n\n\n*MatchID: 1159503*",
    "start": "2026-05-17T15:00:00+00:00",
    "location": "https://twitch.tv/your_twitch_channel"
  },
  {
    "name": "UIC Eclipse vs Golden SpaTUler",
    "description": "🏆 **Prime League Match**\n⚔️ **UIC Eclipse vs Golden SpaTUler**\n\n*Die Roster sind noch nicht vollständig bestätigt. Das offizielle Scouting-Update folgt...*\n\n\n*MatchID: 1163112*",
    "start": "2026-05-17T17:00:00+00:00",
    "location": "https://twitch.tv/your_twitch_channel"
  },
  {
    "name": "UIC Vakuum vs Midlife Macro Masters T2",
    "description": "🏆 **Prime League Match**\n⚔️ **UIC Vakuum vs Midlife Macro Masters T2**\n\n*Die Roster sind noch nicht vollständig bestätigt. Das offizielle Scouting-Update folgt...*\n\n\n*MatchID: 1159557*",
    "start": "2026-05-24T15:00:00+00:00",
    "location": "https://twitch.tv/your_twitch_channel"
  },
  {
    "name": "UIC Spark vs Tiamat´s Abyss",
    "description": "🏆 **Prime League Match**\n⚔️ **UIC Spark vs Tiamat´s Abyss**\n\n*Die Roster sind noch nicht vollständig bestätigt. Das offizielle Scouting-Update folgt...*\n\n\n*MatchID: 1161366*",
    "start": "2026-05-17T17:00:00+00:00",
    "location": "https://twitch.tv/your_twitch_channel"
  },
  {
    "name": "UIC Phoenix vs Zu schlecht für Botis",
    "description": "🏆 **Prime League Match**\n⚔️ **UIC Phoenix vs Zu schlecht für Botis**\n\n*Die Roster sind noch nicht vollständig bestätigt. Das offizielle Scouting-Update folgt...*\n\n\n*MatchID: 1160808*",
    "start": "2026-05-17T17:00:00+00:00",
    "location": "https://twitch.tv/your_twitch_channel"
  },
  {
    "name": "UIC Cyber vs Puppies",
    "description": "🏆 **Prime League Match**\n⚔️ **UIC Cyber vs Puppies**\n\n*Die Roster sind noch nicht vollständig bestätigt. Das offizielle Scouting-Update folgt...*\n\n\n*MatchID: 1161116*",
    "start": "2026-05-17T17:00:00+00:00",
    "location": "https://twitch.tv/your_twitch_channel"
  },
  {
    "name": "UIC Nova vs Senru Excalibur",
    "description": "🏆 **Prime League Match**\n⚔️ **UIC Nova vs Senru Excalibur**\n\n*Die Roster sind noch nicht vollständig bestätigt. Das offizielle Scouting-Update folgt...*\n\n\n*MatchID: 1162131*",
    "start": "2026-05-17T17:00:00+00:00",
    "location": "https://twitch.tv/your_twitch_channel"
  }
]